ciscotmg/__init__.py
ciscotmg/backend.py
ciscotmg/cli.py
ciscotmg/meta.py
ciscotmg/output.py
ciscotmg/result.py
ciscotmg/software.py
ciscotmg/sort.py
ciscotmg-0.3.0.dist-info/LICENSE
ciscotmg-0.3.0.dist-info/METADATA
ciscotmg-0.3.0.dist-info/WHEEL
ciscotmg-0.3.0.dist-info/entry_points.txt
ciscotmg-0.3.0.dist-info/top_level.txt
ciscotmg-0.3.0.dist-info/RECORD
