Metadata-Version: 2.1
Name: ciscotmg
Version: 0.3.0
Summary: Private Python SDK for Cisco TMG Matrix APIs
Home-page: https://github.com/robertcsapo/ciscotmg
Author: Robert Csapo
Author-email: rcsapo@cisco.com
License: MIT; Copyright (c) 2023 Cisco Systems, Inc.
Classifier: Intended Audience :: Developers
Classifier: Natural Language :: English
Classifier: Operating System :: OS Independent
Classifier: Programming Language :: Python
Classifier: Programming Language :: Python :: 3
Classifier: Programming Language :: Python :: 3.6
Classifier: Programming Language :: Python :: 3.7
Classifier: Programming Language :: Python :: 3.8
Classifier: Programming Language :: Python :: 3.9
Classifier: Programming Language :: Python :: 3.10
Classifier: Programming Language :: Python :: Implementation :: CPython
Requires-Python: >=3.6
License-File: LICENSE
Requires-Dist: requests ==2.27.1
Requires-Dist: click ==8.0.3
Requires-Dist: rich ==11.2.0
Requires-Dist: rich-click ==1.0.0
